pyepsg.py
pyepsg-0.4.0.dist-info/DESCRIPTION.rst
pyepsg-0.4.0.dist-info/METADATA
pyepsg-0.4.0.dist-info/RECORD
pyepsg-0.4.0.dist-info/WHEEL
pyepsg-0.4.0.dist-info/metadata.json
pyepsg-0.4.0.dist-info/top_level.txt
