Metadata-Version: 1.1
Name: pyepsg
Version: 0.4.0
Summary: Easy access to the EPSG database via http://epsg.io/
Home-page: https://github.com/rhattersley/pyepsg
Author: Richard Hattersley
Author-email: rhattersley@gmail.com
License: UNKNOWN
Platform: UNKNOWN
Classifier: License :: OSI Approved :: GNU Lesser General Public License v3 (LGPLv3)
Classifier: Programming Language :: Python :: 2
Classifier: Programming Language :: Python :: 2.7
Classifier: Programming Language :: Python :: 3
Classifier: Programming Language :: Python :: 3.3
Classifier: Programming Language :: Python :: 3.4
Classifier: Topic :: Scientific/Engineering :: GIS
